{"resolvedId":"/home/jdw/Code/dxos/dxos/node_modules/.pnpm/inspect-custom-symbol@1.1.1/node_modules/inspect-custom-symbol/browser.js","transforms":[{"name":"vite:load-fallback","result":"module.exports = Symbol.for('nodejs.util.inspect.custom')\n","start":1670465469197,"end":1670465469292},{"name":"vite:react-babel","result":"module.exports = Symbol.for('nodejs.util.inspect.custom')\n","start":1670465469292,"end":1670465469292,"order":"pre"},{"name":"commonjs","result":"import * as commonjsHelpers from \"\u0000commonjsHelpers.js\";\n\nvar browser = Symbol.for('nodejs.util.inspect.custom')\n\nexport default browser;\nexport { browser as __moduleExports };","start":1670465469293,"end":1670465469293,"order":"normal"}]}
