{"resolvedId":"/home/jdw/Code/dxos/dxos/node_modules/.pnpm/phosphor-react@1.4.1_react@18.2.0/node_modules/phosphor-react/dist/icons/Tag.esm.js","transforms":[{"name":"vite:load-fallback","result":"import React, { forwardRef } from 'react';\nimport { renderPathForWeight } from '../lib/index.esm.js';\nimport IconBase from '../lib/IconBase.esm.js';\n\n/* GENERATED FILE */\nvar pathsByWeight = /*#__PURE__*/new Map();\npathsByWeight.set(\"bold\", function (color) {\n  return React.createElement(React.Fragment, null, React.createElement(\"path\", {\n    d: \"M122.7,25.9,42,42,25.9,122.7a8,8,0,0,0,2.2,7.2L132.5,234.3a7.9,7.9,0,0,0,11.3,0l90.5-90.5a7.9,7.9,0,0,0,0-11.3L129.9,28.1A8,8,0,0,0,122.7,25.9Z\",\n    fill: \"none\",\n    stroke: color,\n    strokeLinecap: \"round\",\n    strokeLinejoin: \"round\",\n    strokeWidth: \"24\"\n  }), React.createElement(\"circle\", {\n    cx: \"84\",\n    cy: \"84\",\n    r: \"16\"\n  }));\n});\npathsByWeight.set(\"duotone\", function (color) {\n  return React.createElement(React.Fragment, null, React.createElement(\"path\", {\n    d: \"M122.7,25.9,42,42,25.9,122.7a8,8,0,0,0,2.2,7.2L132.5,234.3a7.9,7.9,0,0,0,11.3,0l90.5-90.5a7.9,7.9,0,0,0,0-11.3L129.9,28.1A8,8,0,0,0,122.7,25.9Z\",\n    opacity: \"0.2\"\n  }), React.createElement(\"path\", {\n    d: \"M122.7,25.9,42,42,25.9,122.7a8,8,0,0,0,2.2,7.2L132.5,234.3a7.9,7.9,0,0,0,11.3,0l90.5-90.5a7.9,7.9,0,0,0,0-11.3L129.9,28.1A8,8,0,0,0,122.7,25.9Z\",\n    fill: \"none\",\n    stroke: color,\n    strokeLinecap: \"round\",\n    strokeLinejoin: \"round\",\n    strokeWidth: \"16\"\n  }), React.createElement(\"circle\", {\n    cx: \"84\",\n    cy: \"84\",\n    r: \"12\"\n  }));\n});\npathsByWeight.set(\"fill\", function () {\n  return React.createElement(React.Fragment, null, React.createElement(\"path\", {\n    d: \"M240,126.9,135.5,22.4A15.9,15.9,0,0,0,121.1,18L40.4,34.2a7.9,7.9,0,0,0-6.2,6.2L18,121.1a15.9,15.9,0,0,0,4.4,14.4L126.9,240a15.9,15.9,0,0,0,22.6,0L240,149.5a15.9,15.9,0,0,0,0-22.6ZM84,96A12,12,0,1,1,96,84,12,12,0,0,1,84,96Z\"\n  }));\n});\npathsByWeight.set(\"light\", function (color) {\n  return React.createElement(React.Fragment, null, React.createElement(\"path\", {\n    d: \"M122.7,25.9,42,42,25.9,122.7a8,8,0,0,0,2.2,7.2L132.5,234.3a7.9,7.9,0,0,0,11.3,0l90.5-90.5a7.9,7.9,0,0,0,0-11.3L129.9,28.1A8,8,0,0,0,122.7,25.9Z\",\n    fill: \"none\",\n    stroke: color,\n    strokeLinecap: \"round\",\n    strokeLinejoin: \"round\",\n    strokeWidth: \"12\"\n  }), React.createElement(\"circle\", {\n    cx: \"84\",\n    cy: \"84\",\n    r: \"10\"\n  }));\n});\npathsByWeight.set(\"thin\", function (color) {\n  return React.createElement(React.Fragment, null, React.createElement(\"path\", {\n    d: \"M122.7,25.9,42,42,25.9,122.7a8,8,0,0,0,2.2,7.2L132.5,234.3a7.9,7.9,0,0,0,11.3,0l90.5-90.5a7.9,7.9,0,0,0,0-11.3L129.9,28.1A8,8,0,0,0,122.7,25.9Z\",\n    fill: \"none\",\n    stroke: color,\n    strokeLinecap: \"round\",\n    strokeLinejoin: \"round\",\n    strokeWidth: \"8\"\n  }), React.createElement(\"circle\", {\n    cx: \"84\",\n    cy: \"84\",\n    r: \"8\"\n  }));\n});\npathsByWeight.set(\"regular\", function (color) {\n  return React.createElement(React.Fragment, null, React.createElement(\"path\", {\n    d: \"M122.7,25.9,42,42,25.9,122.7a8,8,0,0,0,2.2,7.2L132.5,234.3a7.9,7.9,0,0,0,11.3,0l90.5-90.5a7.9,7.9,0,0,0,0-11.3L129.9,28.1A8,8,0,0,0,122.7,25.9Z\",\n    fill: \"none\",\n    stroke: color,\n    strokeLinecap: \"round\",\n    strokeLinejoin: \"round\",\n    strokeWidth: \"16\"\n  }), React.createElement(\"circle\", {\n    cx: \"84\",\n    cy: \"84\",\n    r: \"12\"\n  }));\n});\n\nvar renderPath = function renderPath(weight, color) {\n  return renderPathForWeight(weight, color, pathsByWeight);\n};\n\nvar Tag = /*#__PURE__*/forwardRef(function (props, ref) {\n  return React.createElement(IconBase, Object.assign({\n    ref: ref\n  }, props, {\n    renderPath: renderPath\n  }));\n});\nTag.displayName = \"Tag\";\n\nexport default Tag;\n//# sourceMappingURL=Tag.esm.js.map\n","start":1670465462687,"end":1670465462995},{"name":"vite:react-babel","result":"import React, { forwardRef } from 'react';\nimport { renderPathForWeight } from '../lib/index.esm.js';\nimport IconBase from '../lib/IconBase.esm.js';\n\n/* GENERATED FILE */\nimport { jsx as _jsx } from \"react/jsx-runtime\";\nimport { Fragment as _Fragment } from \"react/jsx-runtime\";\nimport { jsxs as _jsxs } from \"react/jsx-runtime\";\nvar pathsByWeight = /*#__PURE__*/new Map();\npathsByWeight.set(\"bold\", function (color) {\n  return /*#__PURE__*/_jsxs(_Fragment, {\n    children: [/*#__PURE__*/_jsx(\"path\", {\n      d: \"M122.7,25.9,42,42,25.9,122.7a8,8,0,0,0,2.2,7.2L132.5,234.3a7.9,7.9,0,0,0,11.3,0l90.5-90.5a7.9,7.9,0,0,0,0-11.3L129.9,28.1A8,8,0,0,0,122.7,25.9Z\",\n      fill: \"none\",\n      stroke: color,\n      strokeLinecap: \"round\",\n      strokeLinejoin: \"round\",\n      strokeWidth: \"24\"\n    }), /*#__PURE__*/_jsx(\"circle\", {\n      cx: \"84\",\n      cy: \"84\",\n      r: \"16\"\n    })]\n  });\n});\npathsByWeight.set(\"duotone\", function (color) {\n  return /*#__PURE__*/_jsxs(_Fragment, {\n    children: [/*#__PURE__*/_jsx(\"path\", {\n      d: \"M122.7,25.9,42,42,25.9,122.7a8,8,0,0,0,2.2,7.2L132.5,234.3a7.9,7.9,0,0,0,11.3,0l90.5-90.5a7.9,7.9,0,0,0,0-11.3L129.9,28.1A8,8,0,0,0,122.7,25.9Z\",\n      opacity: \"0.2\"\n    }), /*#__PURE__*/_jsx(\"path\", {\n      d: \"M122.7,25.9,42,42,25.9,122.7a8,8,0,0,0,2.2,7.2L132.5,234.3a7.9,7.9,0,0,0,11.3,0l90.5-90.5a7.9,7.9,0,0,0,0-11.3L129.9,28.1A8,8,0,0,0,122.7,25.9Z\",\n      fill: \"none\",\n      stroke: color,\n      strokeLinecap: \"round\",\n      strokeLinejoin: \"round\",\n      strokeWidth: \"16\"\n    }), /*#__PURE__*/_jsx(\"circle\", {\n      cx: \"84\",\n      cy: \"84\",\n      r: \"12\"\n    })]\n  });\n});\npathsByWeight.set(\"fill\", function () {\n  return /*#__PURE__*/_jsx(_Fragment, {\n    children: /*#__PURE__*/_jsx(\"path\", {\n      d: \"M240,126.9,135.5,22.4A15.9,15.9,0,0,0,121.1,18L40.4,34.2a7.9,7.9,0,0,0-6.2,6.2L18,121.1a15.9,15.9,0,0,0,4.4,14.4L126.9,240a15.9,15.9,0,0,0,22.6,0L240,149.5a15.9,15.9,0,0,0,0-22.6ZM84,96A12,12,0,1,1,96,84,12,12,0,0,1,84,96Z\"\n    })\n  });\n});\npathsByWeight.set(\"light\", function (color) {\n  return /*#__PURE__*/_jsxs(_Fragment, {\n    children: [/*#__PURE__*/_jsx(\"path\", {\n      d: \"M122.7,25.9,42,42,25.9,122.7a8,8,0,0,0,2.2,7.2L132.5,234.3a7.9,7.9,0,0,0,11.3,0l90.5-90.5a7.9,7.9,0,0,0,0-11.3L129.9,28.1A8,8,0,0,0,122.7,25.9Z\",\n      fill: \"none\",\n      stroke: color,\n      strokeLinecap: \"round\",\n      strokeLinejoin: \"round\",\n      strokeWidth: \"12\"\n    }), /*#__PURE__*/_jsx(\"circle\", {\n      cx: \"84\",\n      cy: \"84\",\n      r: \"10\"\n    })]\n  });\n});\npathsByWeight.set(\"thin\", function (color) {\n  return /*#__PURE__*/_jsxs(_Fragment, {\n    children: [/*#__PURE__*/_jsx(\"path\", {\n      d: \"M122.7,25.9,42,42,25.9,122.7a8,8,0,0,0,2.2,7.2L132.5,234.3a7.9,7.9,0,0,0,11.3,0l90.5-90.5a7.9,7.9,0,0,0,0-11.3L129.9,28.1A8,8,0,0,0,122.7,25.9Z\",\n      fill: \"none\",\n      stroke: color,\n      strokeLinecap: \"round\",\n      strokeLinejoin: \"round\",\n      strokeWidth: \"8\"\n    }), /*#__PURE__*/_jsx(\"circle\", {\n      cx: \"84\",\n      cy: \"84\",\n      r: \"8\"\n    })]\n  });\n});\npathsByWeight.set(\"regular\", function (color) {\n  return /*#__PURE__*/_jsxs(_Fragment, {\n    children: [/*#__PURE__*/_jsx(\"path\", {\n      d: \"M122.7,25.9,42,42,25.9,122.7a8,8,0,0,0,2.2,7.2L132.5,234.3a7.9,7.9,0,0,0,11.3,0l90.5-90.5a7.9,7.9,0,0,0,0-11.3L129.9,28.1A8,8,0,0,0,122.7,25.9Z\",\n      fill: \"none\",\n      stroke: color,\n      strokeLinecap: \"round\",\n      strokeLinejoin: \"round\",\n      strokeWidth: \"16\"\n    }), /*#__PURE__*/_jsx(\"circle\", {\n      cx: \"84\",\n      cy: \"84\",\n      r: \"12\"\n    })]\n  });\n});\nvar renderPath = function renderPath(weight, color) {\n  return renderPathForWeight(weight, color, pathsByWeight);\n};\nvar Tag = /*#__PURE__*/forwardRef(function (props, ref) {\n  return /*#__PURE__*/_jsx(IconBase, {\n    ...Object.assign({\n      ref: ref\n    }, props, {\n      renderPath: renderPath\n    })\n  });\n});\nTag.displayName = \"Tag\";\nexport default Tag;","start":1670465462995,"end":1670465463001,"order":"pre"}]}
