{
  "id": 1321,
  "name": "InvitationDescriptor",
  "kind": 128,
  "kindString": "Class",
  "flags": {},
  "comment": {
    "summary": [
      {
        "kind": "text",
        "text": "Describes an issued invitation.\n\nCan be serialized to protobuf or JSON.\nInvitations can be interactive or offline.\n\nThis descriptor might also have a bundled secret for authentication in interactive mode."
      }
    ]
  },
  "children": [
    {
      "id": 1331,
      "name": "constructor",
      "kind": 512,
      "kindString": "Constructor",
      "flags": {},
      "sources": [
        {
          "fileName": "packages/sdk/client-services/src/packlets/invitations/invitation-descriptor.ts",
          "line": 73,
          "character": 2,
          "url": "https://github.com/dxos/protocols/blob/main/packages/sdk/client-services/src/packlets/invitations/invitation-descriptor.ts#L73"
        }
      ],
      "signatures": [
        {
          "id": 1332,
          "name": "new InvitationDescriptor",
          "kind": 16384,
          "kindString": "Constructor signature",
          "flags": {},
          "parameters": [
            {
              "id": 1333,
              "name": "type",
              "kind": 32768,
              "kindString": "Parameter",
              "flags": {},
              "type": {
                "type": "reference",
                "name": "Type"
              }
            },
            {
              "id": 1334,
              "name": "swarmKey",
              "kind": 32768,
              "kindString": "Parameter",
              "flags": {},
              "type": {
                "type": "reference",
                "name": "PublicKey"
              }
            },
            {
              "id": 1335,
              "name": "invitation",
              "kind": 32768,
              "kindString": "Parameter",
              "flags": {},
              "type": {
                "type": "reference",
                "name": "Uint8Array",
                "qualifiedName": "Uint8Array",
                "package": "typescript"
              }
            },
            {
              "id": 1336,
              "name": "identityKey",
              "kind": 32768,
              "kindString": "Parameter",
              "flags": {
                "isOptional": true
              },
              "type": {
                "type": "reference",
                "name": "PublicKey"
              }
            },
            {
              "id": 1337,
              "name": "secret",
              "kind": 32768,
              "kindString": "Parameter",
              "flags": {
                "isOptional": true
              },
              "type": {
                "type": "reference",
                "name": "Uint8Array",
                "qualifiedName": "Uint8Array",
                "package": "typescript"
              }
            }
          ],
          "type": {
            "type": "reference",
            "id": 1321,
            "name": "InvitationDescriptor"
          }
        }
      ]
    },
    {
      "id": 1341,
      "name": "identityKey",
      "kind": 1024,
      "kindString": "Property",
      "flags": {
        "isPublic": true,
        "isOptional": true,
        "isReadonly": true
      },
      "sources": [
        {
          "fileName": "packages/sdk/client-services/src/packlets/invitations/invitation-descriptor.ts",
          "line": 77,
          "character": 20,
          "url": "https://github.com/dxos/protocols/blob/main/packages/sdk/client-services/src/packlets/invitations/invitation-descriptor.ts#L77"
        }
      ],
      "type": {
        "type": "reference",
        "name": "PublicKey"
      }
    },
    {
      "id": 1340,
      "name": "invitation",
      "kind": 1024,
      "kindString": "Property",
      "flags": {
        "isPublic": true,
        "isReadonly": true
      },
      "sources": [
        {
          "fileName": "packages/sdk/client-services/src/packlets/invitations/invitation-descriptor.ts",
          "line": 76,
          "character": 20,
          "url": "https://github.com/dxos/protocols/blob/main/packages/sdk/client-services/src/packlets/invitations/invitation-descriptor.ts#L76"
        }
      ],
      "type": {
        "type": "reference",
        "name": "Uint8Array",
        "qualifiedName": "Uint8Array",
        "package": "typescript"
      }
    },
    {
      "id": 1342,
      "name": "secret",
      "kind": 1024,
      "kindString": "Property",
      "flags": {
        "isPublic": true,
        "isOptional": true
      },
      "sources": [
        {
          "fileName": "packages/sdk/client-services/src/packlets/invitations/invitation-descriptor.ts",
          "line": 78,
          "character": 11,
          "url": "https://github.com/dxos/protocols/blob/main/packages/sdk/client-services/src/packlets/invitations/invitation-descriptor.ts#L78"
        }
      ],
      "type": {
        "type": "reference",
        "name": "Uint8Array",
        "qualifiedName": "Uint8Array",
        "package": "typescript"
      }
    },
    {
      "id": 1339,
      "name": "swarmKey",
      "kind": 1024,
      "kindString": "Property",
      "flags": {
        "isPublic": true,
        "isReadonly": true
      },
      "sources": [
        {
          "fileName": "packages/sdk/client-services/src/packlets/invitations/invitation-descriptor.ts",
          "line": 75,
          "character": 20,
          "url": "https://github.com/dxos/protocols/blob/main/packages/sdk/client-services/src/packlets/invitations/invitation-descriptor.ts#L75"
        }
      ],
      "type": {
        "type": "reference",
        "name": "PublicKey"
      }
    },
    {
      "id": 1338,
      "name": "type",
      "kind": 1024,
      "kindString": "Property",
      "flags": {
        "isPublic": true,
        "isReadonly": true
      },
      "sources": [
        {
          "fileName": "packages/sdk/client-services/src/packlets/invitations/invitation-descriptor.ts",
          "line": 74,
          "character": 20,
          "url": "https://github.com/dxos/protocols/blob/main/packages/sdk/client-services/src/packlets/invitations/invitation-descriptor.ts#L74"
        }
      ],
      "type": {
        "type": "reference",
        "name": "Type"
      }
    },
    {
      "id": 1343,
      "name": "hash",
      "kind": 262144,
      "kindString": "Accessor",
      "flags": {},
      "sources": [
        {
          "fileName": "packages/sdk/client-services/src/packlets/invitations/invitation-descriptor.ts",
          "line": 91,
          "character": 6,
          "url": "https://github.com/dxos/protocols/blob/main/packages/sdk/client-services/src/packlets/invitations/invitation-descriptor.ts#L91"
        }
      ],
      "getSignature": {
        "id": 1344,
        "name": "hash",
        "kind": 524288,
        "kindString": "Get signature",
        "flags": {},
        "type": {
          "type": "intrinsic",
          "name": "string"
        }
      }
    },
    {
      "id": 1349,
      "name": "encode",
      "kind": 2048,
      "kindString": "Method",
      "flags": {},
      "sources": [
        {
          "fileName": "packages/sdk/client-services/src/packlets/invitations/invitation-descriptor.ts",
          "line": 126,
          "character": 2,
          "url": "https://github.com/dxos/protocols/blob/main/packages/sdk/client-services/src/packlets/invitations/invitation-descriptor.ts#L126"
        }
      ],
      "signatures": [
        {
          "id": 1350,
          "name": "encode",
          "kind": 4096,
          "kindString": "Call signature",
          "flags": {},
          "type": {
            "type": "intrinsic",
            "name": "string"
          }
        }
      ]
    },
    {
      "id": 1347,
      "name": "toProto",
      "kind": 2048,
      "kindString": "Method",
      "flags": {},
      "sources": [
        {
          "fileName": "packages/sdk/client-services/src/packlets/invitations/invitation-descriptor.ts",
          "line": 115,
          "character": 2,
          "url": "https://github.com/dxos/protocols/blob/main/packages/sdk/client-services/src/packlets/invitations/invitation-descriptor.ts#L115"
        }
      ],
      "signatures": [
        {
          "id": 1348,
          "name": "toProto",
          "kind": 4096,
          "kindString": "Call signature",
          "flags": {},
          "type": {
            "type": "reference",
            "name": "InvitationDescriptor"
          }
        }
      ]
    },
    {
      "id": 1345,
      "name": "toQueryParameters",
      "kind": 2048,
      "kindString": "Method",
      "flags": {},
      "sources": [
        {
          "fileName": "packages/sdk/client-services/src/packlets/invitations/invitation-descriptor.ts",
          "line": 99,
          "character": 2,
          "url": "https://github.com/dxos/protocols/blob/main/packages/sdk/client-services/src/packlets/invitations/invitation-descriptor.ts#L99"
        }
      ],
      "signatures": [
        {
          "id": 1346,
          "name": "toQueryParameters",
          "kind": 4096,
          "kindString": "Call signature",
          "flags": {},
          "comment": {
            "summary": [
              {
                "kind": "text",
                "text": "Exports an InvitationDescriptor to an object suitable for use as query parameters."
              }
            ]
          },
          "type": {
            "type": "reference",
            "id": 1315,
            "name": "InvitationQueryParameters"
          }
        }
      ]
    },
    {
      "id": 1328,
      "name": "decode",
      "kind": 2048,
      "kindString": "Method",
      "flags": {
        "isStatic": true
      },
      "sources": [
        {
          "fileName": "packages/sdk/client-services/src/packlets/invitations/invitation-descriptor.ts",
          "line": 67,
          "character": 9,
          "url": "https://github.com/dxos/protocols/blob/main/packages/sdk/client-services/src/packlets/invitations/invitation-descriptor.ts#L67"
        }
      ],
      "signatures": [
        {
          "id": 1329,
          "name": "decode",
          "kind": 4096,
          "kindString": "Call signature",
          "flags": {},
          "parameters": [
            {
              "id": 1330,
              "name": "code",
              "kind": 32768,
              "kindString": "Parameter",
              "flags": {},
              "type": {
                "type": "intrinsic",
                "name": "string"
              }
            }
          ],
          "type": {
            "type": "reference",
            "id": 1321,
            "name": "InvitationDescriptor"
          }
        }
      ]
    },
    {
      "id": 1325,
      "name": "fromProto",
      "kind": 2048,
      "kindString": "Method",
      "flags": {
        "isStatic": true
      },
      "sources": [
        {
          "fileName": "packages/sdk/client-services/src/packlets/invitations/invitation-descriptor.ts",
          "line": 52,
          "character": 9,
          "url": "https://github.com/dxos/protocols/blob/main/packages/sdk/client-services/src/packlets/invitations/invitation-descriptor.ts#L52"
        }
      ],
      "signatures": [
        {
          "id": 1326,
          "name": "fromProto",
          "kind": 4096,
          "kindString": "Call signature",
          "flags": {},
          "parameters": [
            {
              "id": 1327,
              "name": "invitation",
              "kind": 32768,
              "kindString": "Parameter",
              "flags": {},
              "type": {
                "type": "reference",
                "name": "InvitationDescriptor"
              }
            }
          ],
          "type": {
            "type": "reference",
            "id": 1321,
            "name": "InvitationDescriptor"
          }
        }
      ]
    },
    {
      "id": 1322,
      "name": "fromQueryParameters",
      "kind": 2048,
      "kindString": "Method",
      "flags": {
        "isStatic": true
      },
      "sources": [
        {
          "fileName": "packages/sdk/client-services/src/packlets/invitations/invitation-descriptor.ts",
          "line": 39,
          "character": 9,
          "url": "https://github.com/dxos/protocols/blob/main/packages/sdk/client-services/src/packlets/invitations/invitation-descriptor.ts#L39"
        }
      ],
      "signatures": [
        {
          "id": 1323,
          "name": "fromQueryParameters",
          "kind": 4096,
          "kindString": "Call signature",
          "flags": {},
          "parameters": [
            {
              "id": 1324,
              "name": "queryParameters",
              "kind": 32768,
              "kindString": "Parameter",
              "flags": {},
              "type": {
                "type": "reference",
                "id": 1315,
                "name": "InvitationQueryParameters"
              }
            }
          ],
          "type": {
            "type": "reference",
            "id": 1321,
            "name": "InvitationDescriptor"
          }
        }
      ]
    }
  ],
  "groups": [
    {
      "title": "Constructors",
      "children": [
        1331
      ]
    },
    {
      "title": "Properties",
      "children": [
        1341,
        1340,
        1342,
        1339,
        1338
      ]
    },
    {
      "title": "Accessors",
      "children": [
        1343
      ]
    },
    {
      "title": "Methods",
      "children": [
        1349,
        1347,
        1345,
        1328,
        1325,
        1322
      ]
    }
  ],
  "sources": [
    {
      "fileName": "packages/sdk/client-services/src/packlets/invitations/invitation-descriptor.ts",
      "line": 38,
      "character": 13,
      "url": "https://github.com/dxos/protocols/blob/main/packages/sdk/client-services/src/packlets/invitations/invitation-descriptor.ts#L38"
    }
  ]
}